netlink/core/__init__.py
netlink/core/attribute_mapping.py
netlink/core/cli.py
netlink/core/config.py
netlink/core/configuration.py
netlink/core/generation.py
netlink/core/mapping.py
netlink/core/named_mapping.py
netlink/core/singleton.py
netlink_core-1.1.2.dist-info/entry_points.txt
netlink_core-1.1.2.dist-info/LICENSE.md
netlink_core-1.1.2.dist-info/WHEEL
netlink_core-1.1.2.dist-info/METADATA
netlink_core-1.1.2.dist-info/RECORD
