Metadata-Version: 2.1
Name: netlink-core
Version: 1.1.2
Summary: Core components of NetLink tools
Home-page: https://gitlab.com/netlink_python/netlink-core.git
License: MIT
Author: Bernhard Radermacher
Author-email: bernhard.radermacher@netlink-consulting.com
Requires-Python: >=3.8,<=3.12
Classifier: License :: OSI Approved :: MIT License
Classifier: Programming Language :: Python :: 3
Classifier: Programming Language :: Python :: 3.10
Classifier: Programming Language :: Python :: 3.8
Classifier: Programming Language :: Python :: 3.9
Classifier: Topic :: Software Development
Requires-Dist: PyYAML (>=6.0.1)
Requires-Dist: toml (>=0.10.2)
Project-URL: Repository, https://gitlab.com/netlink_python/netlink-core.git
